pytargetingutilities/__init__.py
pytargetingutilities/aws/e2/helper.py
pytargetingutilities/aws/e2/run_command.py
pytargetingutilities/aws/s3/__init__.py
pytargetingutilities/aws/s3/base_paginator.py
pytargetingutilities/aws/s3/helper.py
pytargetingutilities/aws/s3/iterator.py
pytargetingutilities/aws/s3/line_iterator.py
pytargetingutilities/tools/__init__.py
pytargetingutilities/tools/hash.py
pytargetingutilities/tools/log.py
pytargetingutilities/urltokenizer/__init__.py
pytargetingutilities/urltokenizer/regex_url_tokenizer.py
pytargetingutilities-1.1.0.dist-info/LICENSE
pytargetingutilities-1.1.0.dist-info/METADATA
pytargetingutilities-1.1.0.dist-info/WHEEL
pytargetingutilities-1.1.0.dist-info/top_level.txt
pytargetingutilities-1.1.0.dist-info/RECORD
